llm_loop/__init__.py
llm_loop/cli.py
llm_loop/config/__init__.py
llm_loop/config/settings.py
llm_loop/core/__init__.py
llm_loop/core/conversation.py
llm_loop/core/prompts.py
llm_loop/core/tools.py
llm_loop/plugins/__init__.py
llm_loop/plugins/dev_tools.py
llm_loop/utils/__init__.py
llm_loop/utils/exceptions.py
llm_loop/utils/types.py
llm_loop/utils/validation.py
llm_loop_plugin-0.2.2.dist-info/licenses/LICENSE
llm_loop_plugin-0.2.2.dist-info/METADATA
llm_loop_plugin-0.2.2.dist-info/WHEEL
llm_loop_plugin-0.2.2.dist-info/entry_points.txt
llm_loop_plugin-0.2.2.dist-info/top_level.txt
llm_loop_plugin-0.2.2.dist-info/RECORD
