Metadata-Version: 2.4
Name: llm-loop-plugin
Version: 0.2.2
Summary: An LLM CLI plugin to loop tool calls with turn limits and custom system prompts.
Author-email: nibzard <wave@nibzard.com>
License-Expression: MIT
Project-URL: Homepage, https://github.com/nibzard/llm-loop
Project-URL: Repository, https://github.com/nibzard/llm-loop
Project-URL: Bug Tracker, https://github.com/nibzard/llm-loop/issues
Project-URL: Changelog, https://github.com/nibzard/llm-loop/releases
Classifier: Development Status :: 4 - Beta
Classifier: Intended Audience :: Developers
Classifier: Topic :: Software Development :: Libraries :: Python Modules
Classifier: Topic :: Utilities
Classifier: Programming Language :: Python :: 3
Classifier: Programming Language :: Python :: 3.8
Classifier: Programming Language :: Python :: 3.9
Classifier: Programming Language :: Python :: 3.10
Classifier: Programming Language :: Python :: 3.11
Classifier: Programming Language :: Python :: 3.12
Classifier: Environment :: Console
Classifier: Operating System :: OS Independent
Requires-Python: >=3.8
License-File: LICENSE
Requires-Dist: llm>=0.26
Requires-Dist: click>=8.0.0
Provides-Extra: dev
Requires-Dist: pytest>=7.0.0; extra == "dev"
Requires-Dist: pytest-cov>=4.0.0; extra == "dev"
Requires-Dist: mypy>=1.0.0; extra == "dev"
Requires-Dist: ruff>=0.1.0; extra == "dev"
Requires-Dist: black>=23.0.0; extra == "dev"
Dynamic: license-file
